pht/__init__.py
dpv-0.0.1.dist-info/METADATA
dpv-0.0.1.dist-info/WHEEL
dpv-0.0.1.dist-info/license.md
dpv-0.0.1.dist-info/top_level.txt
dpv-0.0.1.dist-info/RECORD
