Metadata-Version: 2.1
Name: dpv
Version: 0.0.1
Summary: TBA
Author-email: Leevi Olander <leevi.olander@live.com>
Classifier: Programming Language :: Python :: 3
Classifier: License :: OSI Approved :: MIT License
Classifier: Operating System :: OS Independent
Requires-Python: >=3.7
License-File: license.md
